[
    {
        "ParameterKey": "HostedZone",
        "ParameterValue": "Z2LSP7EWLHSOQQ"
    },
    {
        "ParameterKey": "KeyName",
        "ParameterValue": "tonynv"
    },
    {
        "ParameterKey": "DTRFQDN",
        "ParameterValue": "ap-southeast-2-dtr.awsqs.com"
    },
    {
        "ParameterKey": "UCPFQDN",
        "ParameterValue": "ap-southeast-2-ucp.awsqs.com"
    },
    {
        "ParameterKey": "APPFQDN",
        "ParameterValue": "ap-southeast-2-app.awsqs.com"
    },
    {
        "ParameterKey": "License",
        "ParameterValue": "https://s3.amazonaws.com/quickstart-temp-lic/docker/docker_subscription.lic"
    }
]
